mcp_pandas/__init__.py
mcp_pandas/server.py
mcp_pandas-0.5.1.dist-info/METADATA
mcp_pandas-0.5.1.dist-info/WHEEL
mcp_pandas-0.5.1.dist-info/entry_points.txt
mcp_pandas-0.5.1.dist-info/RECORD
