Metadata-Version: 2.4
Name: mcp-pandas
Version: 0.5.1
Summary: Add your description here
Author-email: Anthony Shaw <anthony.p.shaw@gmail.com>
Requires-Python: >=3.10
Requires-Dist: matplotlib>=3.10.1
Requires-Dist: mcp
Requires-Dist: openpyxl>=3.1.5
Requires-Dist: pandas
